
    {
        "fromDate": 1619114400000,
        "toDate": 1620064800000,
        "billReferralDataList": [
            {
                "refDocNo": 1016217,
                "doctorId": "157",
                "doctorName": "PROF. DR. SAMSAD JAHAN (SHELLY), MBBS, MS",
                "address": "BIRDEM HOSPITAL / JBFH",
                "salesrepNo": 1000254,
                "empId": "35",
                "empName": "I TEAM (RATAN CHANDRA BAISNAB + MD. KHORSHED ALAM)",
                "invoiceNo": 1210000487729,
                "invoiceId": "121004419",
                "companyNo": 1,
                "invoiceDate": 1619287200000,
                "lastPayDate": 1619287200000,
                "deptName": "DEPARTMENT OF X-RAY",
                "itemName": "X-RAY HIP joint (LT. and RT.) B/V",
                "intExtFlag": 0,
                "secondRefDocNo": null,
                "refPaid": 0,
                "refHideFlag": 0,
                "itemRate": 1000,
                "totRefAmt": 200,
                "cliDisc": 0,
                "docDisc": 200,
                "netRefAmt": 160,
                "due": 700,
                "fromInvoiceDate": null,
                "toInvoiceDate": null
            },
            {
                "refDocNo": 1008367,
                "doctorId": "X19408",
                "doctorName": "DR. SHISHIR CHAKRABARTY, MBBS.",
                "address": "TITAS GAS.",
                "salesrepNo": null,
                "empId": null,
                "empName": null,
                "invoiceNo": 1210000487669,
                "invoiceId": "121004418",
                "companyNo": 1,
                "invoiceDate": 1619287200000,
                "lastPayDate": 1619287200000,
                "deptName": "DEPARTMENT OF PATHOLOGY",
                "itemName": "Real Time PCR for COVID-19",
                "intExtFlag": 0,
                "secondRefDocNo": null,
                "refPaid": 0,
                "refHideFlag": 0,
                "itemRate": 3500,
                "totRefAmt": 350,
                "cliDisc": 0,
                "docDisc": 200,
                "netRefAmt": 330,
                "due": 0,
                "fromInvoiceDate": null,
                "toInvoiceDate": null
            },
            {
                "refDocNo": 1008016,
                "doctorId": "MA40",
                "doctorName": "DR MARZINA KAJOL, SACMO",
                "address": "AMIN BAZAR HOSPITAL, AMINBAZAR, SAVAR",
                "salesrepNo": 1000229,
                "empId": "34",
                "empName": "A2 TEAM (Md. Shariful Islam+",
                "invoiceNo": 1210000488530,
                "invoiceId": "121004436",
                "companyNo": 1,
                "invoiceDate": 1619546400000,
                "lastPayDate": null,
                "deptName": "DEPARTMENT OF SPECIAL PATHOLOGY",
                "itemName": "T3",
                "intExtFlag": 0,
                "secondRefDocNo": null,
                "refPaid": 0,
                "refHideFlag": 0,
                "itemRate": 700,
                "totRefAmt": 280,
                "cliDisc": 0,
                "docDisc": 0,
                "netRefAmt": 280,
                "due": 730,
                "fromInvoiceDate": null,
                "toInvoiceDate": null
            },
            {
                "refDocNo": 1003297,
                "doctorId": " SH55001",
                "doctorName": "Dr. Md. Shaiful Islam, MBBS, FCPS",
                "address": "VASANTAC DIAGONISTIC CENTER, VASANTAC BAZAR",
                "salesrepNo": 1000248,
                "empId": "27",
                "empName": "MD. ASHIK",
                "invoiceNo": 1210000488529,
                "invoiceId": "121004435",
                "companyNo": 1,
                "invoiceDate": 1619546400000,
                "lastPayDate": null,
                "deptName": "DEPARTMENT OF SPECIAL PATHOLOGY",
                "itemName": "T3",
                "intExtFlag": 0,
                "secondRefDocNo": 1003297,
                "refPaid": 0,
                "refHideFlag": 0,
                "itemRate": 700,
                "totRefAmt": 280,
                "cliDisc": 0,
                "docDisc": 0,
                "netRefAmt": 280,
                "due": 730,
                "fromInvoiceDate": null,
                "toInvoiceDate": null
            },
            {
                "refDocNo": 1003297,
                "doctorId": " SH55001",
                "doctorName": "Dr. Md. Shaiful Islam, MBBS, FCPS",
                "address": "VASANTAC DIAGONISTIC CENTER, VASANTAC BAZAR",
                "salesrepNo": 1000248,
                "empId": "27",
                "empName": "MD. ASHIK",
                "invoiceNo": 1210000488468,
                "invoiceId": "121004433",
                "companyNo": 1,
                "invoiceDate": 1619546400000,
                "lastPayDate": 1619546400000,
                "deptName": "DEPARTMENT OF SPECIAL PATHOLOGY",
                "itemName": "T3, T4, TSH",
                "intExtFlag": 0,
                "secondRefDocNo": 1003297,
                "refPaid": 0,
                "refHideFlag": 0,
                "itemRate": 2100,
                "totRefAmt": 210,
                "cliDisc": 0,
                "docDisc": 0,
                "netRefAmt": 210,
                "due": 120,
                "fromInvoiceDate": null,
                "toInvoiceDate": null
            },
            {
                "refDocNo": 1003297,
                "doctorId": " SH55001",
                "doctorName": "Dr. Md. Shaiful Islam, MBBS, FCPS",
                "address": "VASANTAC DIAGONISTIC CENTER, VASANTAC BAZAR",
                "salesrepNo": 1000248,
                "empId": "27",
                "empName": "MD. ASHIK",
                "invoiceNo": 1210000488468,
                "invoiceId": "121004433",
                "companyNo": 1,
                "invoiceDate": 1619546400000,
                "lastPayDate": 1619546400000,
                "deptName": "DEPARTMENT OF PATHOLOGY",
                "itemName": "CBC",
                "intExtFlag": 0,
                "secondRefDocNo": 1003297,
                "refPaid": 0,
                "refHideFlag": 0,
                "itemRate": 500,
                "totRefAmt": 200,
                "cliDisc": 0,
                "docDisc": 0,
                "netRefAmt": 200,
                "due": 120,
                "fromInvoiceDate": null,
                "toInvoiceDate": null
            },
            {
                "refDocNo": 1002998,
                "doctorId": "0152",
                "doctorName": "Dr Md Golam Nabi, MBBS, FCPS",
                "address": "Dept. Of Physical Med.(BSMMU). 01715698367",
                "salesrepNo": 1000254,
                "empId": "35",
                "empName": "I TEAM (RATAN CHANDRA BAISNAB + MD. KHORSHED ALAM)",
                "invoiceNo": 1210000488393,
                "invoiceId": "121004427",
                "companyNo": 1,
                "invoiceDate": 1619546400000,
                "lastPayDate": 1619546400000,
                "deptName": "DEPARTMENT OF SPECIAL PATHOLOGY",
                "itemName": "TSH",
                "intExtFlag": 0,
                "secondRefDocNo": null,
                "refPaid": 0,
                "refHideFlag": 0,
                "itemRate": 700,
                "totRefAmt": 70,
                "cliDisc": 0,
                "docDisc": 0,
                "netRefAmt": 70,
                "due": 1530,
                "fromInvoiceDate": null,
                "toInvoiceDate": null
            },
            {
                "refDocNo": 1002998,
                "doctorId": "0152",
                "doctorName": "Dr Md Golam Nabi, MBBS, FCPS",
                "address": "Dept. Of Physical Med.(BSMMU). 01715698367",
                "salesrepNo": 1000254,
                "empId": "35",
                "empName": "I TEAM (RATAN CHANDRA BAISNAB + MD. KHORSHED ALAM)",
                "invoiceNo": 1210000488393,
                "invoiceId": "121004427",
                "companyNo": 1,
                "invoiceDate": 1619546400000,
                "lastPayDate": 1619546400000,
                "deptName": "DEPARTMENT OF PATHOLOGY",
                "itemName": "CBC With Film",
                "intExtFlag": 0,
                "secondRefDocNo": null,
                "refPaid": 0,
                "refHideFlag": 0,
                "itemRate": 800,
                "totRefAmt": 320,
                "cliDisc": 0,
                "docDisc": 0,
                "netRefAmt": 320,
                "due": 1530,
                "fromInvoiceDate": null,
                "toInvoiceDate": null
            },
            {
                "refDocNo": 1002629,
                "doctorId": "0055",
                "doctorName": "DR ASIF HASAN KHAN, MBBS(DHAKA), BCS, FCPS(P-II) (MEDICINE)",
                "address": "BISMILLAH PHARMACY, H- 33, B-B, SEC-13, MIRPUR. 01914079923, 01744462246.",
                "salesrepNo": 1000237,
                "empId": "19",
                "empName": "MR. M. S. ALAM TARAFDER",
                "invoiceNo": 1210000488152,
                "invoiceId": "121004423",
                "companyNo": 1,
                "invoiceDate": 1619460000000,
                "lastPayDate": 1619460000000,
                "deptName": "DEPARTMENT OF PATHOLOGY",
                "itemName": "Creatinine Clearance Rate (CCR), Albumin (Urine), CBC With Film",
                "intExtFlag": 4,
                "secondRefDocNo": null,
                "refPaid": 0,
                "refHideFlag": 0,
                "itemRate": 1700,
                "totRefAmt": 680,
                "cliDisc": 0,
                "docDisc": 344,
                "netRefAmt": 543,
                "due": 1000,
                "fromInvoiceDate": null,
                "toInvoiceDate": null
            },
            {
                "refDocNo": 1001486,
                "doctorId": "0054",
                "doctorName": "DR. AFROZA BEGUM,  FCPS",
                "address": "Doctors Clinic\nRajani Gandha Super Market\nDhaka Cantt.\n\n",
                "salesrepNo": 1000229,
                "empId": "34",
                "empName": "A2 TEAM (Md. Shariful Islam+",
                "invoiceNo": 1210000488470,
                "invoiceId": "121004434",
                "companyNo": 1,
                "invoiceDate": 1619546400000,
                "lastPayDate": null,
                "deptName": "DEPARTMENT OF SPECIAL PATHOLOGY",
                "itemName": "T3",
                "intExtFlag": 1,
                "secondRefDocNo": 1001486,
                "refPaid": 0,
                "refHideFlag": 0,
                "itemRate": 700,
                "totRefAmt": 280,
                "cliDisc": 0,
                "docDisc": 0,
                "netRefAmt": 280,
                "due": 730,
                "fromInvoiceDate": null,
                "toInvoiceDate": null
            },
            {
                "refDocNo": 1001419,
                "doctorId": "0056",
                "doctorName": "Dr Kaniz Fatema Ananya, MBBS,PGT",
                "address": "UPHCP/PKSP.M-7 /GLAXY HOSPT .MIRPUR-10. 01713164919. N.H.F. MIR-2",
                "salesrepNo": null,
                "empId": null,
                "empName": null,
                "invoiceNo": 1210000487730,
                "invoiceId": "121004420",
                "companyNo": 1,
                "invoiceDate": 1619287200000,
                "lastPayDate": 1619373600000,
                "deptName": "DEPARTMENT OF X-RAY",
                "itemName": "X-RAY Pelvis WITH BOTH HIP JT AP (Digital)",
                "intExtFlag": 3,
                "secondRefDocNo": null,
                "refPaid": 0,
                "refHideFlag": 0,
                "itemRate": 450,
                "totRefAmt": 90,
                "cliDisc": 0,
                "docDisc": 0,
                "netRefAmt": 90,
                "due": 800,
                "fromInvoiceDate": null,
                "toInvoiceDate": null
            },
            {
                "refDocNo": 1001419,
                "doctorId": "0056",
                "doctorName": "Dr Kaniz Fatema Ananya, MBBS,PGT",
                "address": "UPHCP/PKSP.M-7 /GLAXY HOSPT .MIRPUR-10. 01713164919. N.H.F. MIR-2",
                "salesrepNo": null,
                "empId": null,
                "empName": null,
                "invoiceNo": 1210000487730,
                "invoiceId": "121004420",
                "companyNo": 1,
                "invoiceDate": 1619287200000,
                "lastPayDate": 1619373600000,
                "deptName": "DEPARTMENT OF SPECIAL PATHOLOGY",
                "itemName": "T3",
                "intExtFlag": 3,
                "secondRefDocNo": null,
                "refPaid": 0,
                "refHideFlag": 0,
                "itemRate": 700,
                "totRefAmt": 280,
                "cliDisc": 0,
                "docDisc": 0,
                "netRefAmt": 280,
                "due": 800,
                "fromInvoiceDate": null,
                "toInvoiceDate": null
            },
            {
                "refDocNo": 1001419,
                "doctorId": "0056",
                "doctorName": "Dr Kaniz Fatema Ananya, MBBS,PGT",
                "address": "UPHCP/PKSP.M-7 /GLAXY HOSPT .MIRPUR-10. 01713164919. N.H.F. MIR-2",
                "salesrepNo": null,
                "empId": null,
                "empName": null,
                "invoiceNo": 1210000487730,
                "invoiceId": "121004420",
                "companyNo": 1,
                "invoiceDate": 1619287200000,
                "lastPayDate": 1619373600000,
                "deptName": "DEPARTMENT OF PATHOLOGY",
                "itemName": "CBC With Film",
                "intExtFlag": 3,
                "secondRefDocNo": null,
                "refPaid": 0,
                "refHideFlag": 0,
                "itemRate": 800,
                "totRefAmt": 320,
                "cliDisc": 80,
                "docDisc": 80,
                "netRefAmt": 256,
                "due": 800,
                "fromInvoiceDate": null,
                "toInvoiceDate": null
            },
            {
                "refDocNo": 1001419,
                "doctorId": "0056",
                "doctorName": "Dr Kaniz Fatema Ananya, MBBS,PGT",
                "address": "UPHCP/PKSP.M-7 /GLAXY HOSPT .MIRPUR-10. 01713164919. N.H.F. MIR-2",
                "salesrepNo": null,
                "empId": null,
                "empName": null,
                "invoiceNo": 1210000487730,
                "invoiceId": "121004420",
                "companyNo": 1,
                "invoiceDate": 1619287200000,
                "lastPayDate": 1619373600000,
                "deptName": "DEPARTMENT OF PATHOLOGY",
                "itemName": "Blood for C/S, Serum Creatinine",
                "intExtFlag": 3,
                "secondRefDocNo": null,
                "refPaid": 0,
                "refHideFlag": 0,
                "itemRate": 1400,
                "totRefAmt": 560,
                "cliDisc": 0,
                "docDisc": 0,
                "netRefAmt": 560,
                "due": 800,
                "fromInvoiceDate": null,
                "toInvoiceDate": null
            }
        ]
    }
